apptoolkit/.DS_Store
apptoolkit/__init__.py
apptoolkit/__init__.pyc
apptoolkit/ios_mapping.json
apptoolkit/shell.py
apptoolkit-0.0.8.dist-info/DESCRIPTION.rst
apptoolkit-0.0.8.dist-info/METADATA
apptoolkit-0.0.8.dist-info/RECORD
apptoolkit-0.0.8.dist-info/WHEEL
apptoolkit-0.0.8.dist-info/metadata.json
apptoolkit-0.0.8.dist-info/top_level.txt
apptoolkit-0.0.8.dist-info/zip-safe
