Metadata-Version: 2.0
Name: apptoolkit
Version: 0.0.8
Summary: apptoolkit
Home-page: https://github.com/logan62334/python-apptoolkit.git
Author: mafei
Author-email: logan62334@gmail.com
License: MIT Licence
Platform: any
